pysts/__init__.py
pysts/__main__.py
pysts/dash/__init__.py
pysts/dash/app.py
pysts/dash/baseline.py
pysts/dash/config.py
pysts/dash/utils.py
pysts/dash/components/__init__.py
pysts/dash/components/alert.py
pysts/dash/components/base.py
pysts/dash/components/base_component.py
pysts/dash/components/download.py
pysts/dash/components/dropdown.py
pysts/dash/components/file_browser.py
pysts/dash/components/modal.py
pysts/dash/components/tabs.py
pysts/dash/components/uploader.py
pysts/dash/edit/__init__.py
pysts/dash/edit/callbacks.py
pysts/dash/edit/layout.py
pysts/dash/example_pages/NewPage.py
pysts/dash/example_pages/__init__.py
pysts/dash/example_pages/amplitudes.py
pysts/dash/example_pages/edit.py
pysts/dash/example_pages/main.py
pysts/dash/example_pages/overview.py
pysts/db/__init__.py
pysts/db/influxdb/__init__.py
pysts/db/influxdb/classes.py
pysts/db/mongodb/__init__.py
pysts/db/mongodb/classes.py
pysts/db/mongodb/engine.py
pysts/db/mongodb/process.py
pysts/db/mongodb/utils.py
pysts/db/reldb/__init__.py
pysts/db/reldb/analyzer.py
pysts/db/reldb/buildware.py
pysts/db/reldb/classes.py
pysts/db/reldb/db.py
pysts/gui/__init__.py
pysts/gui/dash/__init__.py
pysts/gui/dash/alert.py
pysts/gui/dash/base.py
pysts/gui/dash/base_component.py
pysts/gui/dash/download.py
pysts/gui/dash/dropdown.py
pysts/gui/dash/file_browser.py
pysts/gui/dash/modal.py
pysts/gui/dash/tabs.py
pysts/gui/dash/uploader.py
pysts/gui/dash/utils.py
pysts/gui/dash/components/__init__.py
pysts/gui/pyqt/__init__.py
pysts/gui/tkinter/__init__.py
pysts/gui/tkinter/app.py
pysts/gui/tkinter/component.py
pysts/gui/tkinter/frame.py
pysts/gui/tkinter/window.py
pysts/listeners/__init__.py
pysts/listeners/listener.py
pysts/listeners/physical.py
pysts/listeners/time.py
pysts/notebook/__init__.py
pysts/notebook/convert.py
pysts/notebook/notebook.py
pysts/notebook/utils.py
pysts/notebook/report/__init__.py
pysts/notebook/report/app.py
pysts/notebook/report/record.py
pysts/notebook/report/widget_utils.py
pysts-0.9.45.dist-info/LICENSE
pysts-0.9.45.dist-info/METADATA
pysts-0.9.45.dist-info/WHEEL
pysts-0.9.45.dist-info/top_level.txt
pysts-0.9.45.dist-info/RECORD
