Metadata-Version: 2.1
Name: pysts
Version: 0.9.45
Summary: Basic python utilities
Home-page: https://github.com/sdswart/pysts.git
Author: Stephen Swart
License: MIT
Download-URL: https://github.com/sdswart/pysts/archive/v_0.9.45.tar.gz
Keywords: utilities
Platform: UNKNOWN
Classifier: Programming Language :: Python :: 3
Classifier: License :: OSI Approved :: MIT License
Classifier: Operating System :: OS Independent
Requires-Dist: setuptools
Requires-Dist: wheel
Requires-Dist: twine
Requires-Dist: numpy
Requires-Dist: pandas
Requires-Dist: plotly
Requires-Dist: dash (==1.18.0)
Requires-Dist: quart
Requires-Dist: quart-compress
Requires-Dist: dash-core-components
Requires-Dist: dash-bootstrap-components
Requires-Dist: dash-html-components
Requires-Dist: dash-table
